Workbook

Sheet Introduction
U1: 2025
A2: Ce cahier d’exercices est l’outil d’auto-évaluation de la version 2025 du CyberFundamentals Framework. Le CyberFundamentals Framework est développé par le Centre pour la cybersécurité Belgique (CCB), qui opère sous l’autorité du Premier ministre belge. Le cadre comprend un ensemble de mesures concrètes pour protéger les données, réduire considérablement le risque des cyberattaques les plus courantes et augmenter la cyber-résilience des organisations. Le cadre peut être utilisé à la fois à des fins volontaires et obligatoires. En cas d’utilisation volontaire, il est considéré comme le Système National de Certification pour la Certification de Cybersécurité mettant en œuvre le mandat statutaire du CCB (AR 10 Oct 2014, Art. 3 8°). Pour l’utilisation obligatoire du système de certification, les lois et règlements imposant l’utilisation obligatoire s’appliquent. L’auto-déclaration de conformité Cyberfundamentals est basée sur une auto-évaluation à l’aide de cet outil. L’auto-déclaration peut être vérifiée par un organisme d’évaluation de la conformité (CAB) tiers indépendant et aboutira ensuite à un label, une allégation vérifiée ou un certificat conformément au système d’évaluation de la conformité. | Q2: Change Log
Q3: Date | R3: Reason for change
Q4: 45931 | R4: Initial release in the context of CyFun® version 2025
A19: Itinéraire: (1) Chaque onglet « détails » contient les commandes du niveau respectif du cadre cyberfundamentals (BASIC-IMPORTANT- ESSENTIAL). L’évaluation de chaque contrôle s’articule autour de 2 axes : la manière dont le contrôle est documenté (maturité de la documentation) et la manière dont cette documentation est mise en œuvre (maturité de la mise en œuvre). La maturité de chacun des contrôles est évaluée à l’aide de l’explication de l’onglet Niveaux de maturité. (2) Sur la base de l’évaluation et en fonction du niveau de maturité, une valeur de 1 à 5 est saisie par contrôle dans l’onglet « détails » de chaque niveau d’assurance. Ce niveau est déterminé à la fois pour la maturité de la documentation et la maturité de l’implémentation. (3) L’onglet « résumé » des niveaux cyberfondamentaux respectifs indique le score de maturité qui détermine si l’on est conforme ou non au système d’évaluation de la conformité. Les scores cibles indiqués dans l’onglet « résumé » sont ceux déterminés dans le système d’évaluation de la conformité. | Q19: Applicable version of the CyberFundamentels framework
Q20: Version | R20: requirements | T20: 45931
Q21: Version | R21: CAS (**) | T21: 45723
Q23: (*) NAB: National Accreditation Body (BE: BELAC)
Q24: (**) CAS: Conformity Assessment Scheme
Q26: Self-Assessment Completion date
Q27: This self-assessment was completed by the entity on: | T27: 45931
A31: The CyberFundamentals Framework, its tools and user instructions are available on: | G31: www.cyfun.eu
A32: The CyberFundamentals Conformity Assessment Scheme is available on: | G32: www.cyfun.eu
A33: Questions and feedback regarding this framework can be addressed to: | G33: certification@ccb.belgium.be
A36: NOTE: Since the CyFun® Self-Assessment Tool is an element of the CyFun® Conformity Assessment Scheme that operates under accreditation, it is not possible to unprotect cells or activate all MS Excel features.

Sheet Maturity Levels
A1: Maturity Level | B1: Maturity Value | C1: Documentation Maturity Expectation of Documentation Maturity Level | D1: Implementation Maturity Expectation of Implementation Maturity Level | F1: Maturity level thresholds BASIC
A2: Level 1 - Initial | B2: 1 | C2: No Process documentation or not formally approved by management. | D2: Standard process does not exist. | F2: Each Key Measure Maturity level | G2: ≥ 2,5/5
A3: Level 2 - Repeatable | B3: 2 | C3: Formally approved Process documentation exists but not reviewed in the previous 2 years. | D3: Ad-hoc process exists and is done informally. | F3: Each Category Maturity level | G3: n/a
A4: Level 3 - Defined | B4: 3 | C4: Formally approved Process documentation exists, and exceptions are documented and approved. Documented & approved exceptions < 5% of the time. | D4: Formal process exists and is implemented. Evidence available for most activities. Less than 10% process exceptions. | F4: Total Maturity level (average) | G4: ≥ 2,5/5
A5: Level 4 - Managed | B5: 4 | C5: Formally approved Process documentation exists, and exceptions are documented and approved. Documented & approved exceptions < 3% of the time. | D5: Formal process exists and is implemented. Evidence available for all activities. Detailed metrics of the process are captured and reported. Minimal target for metrics has been established. Less than 5% of process exceptions.
A6: Level 5 - Optimizing | B6: 5 | C6: Formally approved Process documentation exists, and exceptions are documented and approved. Documented & approved exceptions < 0,5% of the time. | D6: Formal process exists and is implemented. Evidence available for all activities. Detailed metrics of the process are captured and reported. Minimal target for metrics has been established and continually improving. Less than 1% of process exceptions.
A8: Assessment definitions
A9: Documentation Maturity: | B9: The Documentation Maturity evaluation measures how well your written rules and procedures satisfy the controls of the CyberFundamentals Framework
A10: Implementation Maturity: | B10: The Implementation Maturity evaluation assess how mature your actual operational practices are in relation to the CyberFundamentals Framework
A12: More information on maturity levels is available in the “Completing your self-assessment” section of the CyberFundamentals Toolbox (www.cyfun.be).

Sheet GOVERN
A1: TLP: AMBER CyberFundamentals Tool version: | C1: =Introduction!Q4 -> 45931 | D1: Self-Assessment Completion Date: | E1: =Introduction!T27 -> 45931 | F1: BASIC
A2: Categorie | B2: Mesure de Gouvernance | C2: Mesure clé | D2: Sous categorie | E2: Exigence | F2: Documentation Score | G2: Score de mise en œuvre | H2: Sous-catégorie Documentation Score de maturité | I2: Sous-catégoriede la mise en œuvre Score de maturité | J2: Catégorie Documentation Score de Maturité | K2: Catégorie : Score de maturité de mise en œuvre | L2: Commentaires et/ou informations complémentaires | M2: Commentaires de l’évaluateur
A3: Contexte organisationnel (GV.OC) : Les circonstances (mission, attentes des parties prenantes, dépendances et exigences légales, réglementaires et contractuelles) entourant les décisions de l’organisation en matière de gestion des risques de cybersécurité sont comprises. | D3: GV. OC-03 : Les exigences légales, réglementaires et contractuelles en matière de cybersécurité sont comprises et gérées. | E3: GV. OC-03.1 : Les exigences légales et réglementaires en matière d’information et de cybersécurité doivent être identifiées et mises en œuvre. | F3: 1 | G3: 1 | H3: =AVERAGE(F3) -> 1 | I3: =AVERAGE(G3) -> 1 | J3: =H3 -> 1 | K3: =I3 -> 1
A4: Stratégie de gestion des risques (GV.RM) : Les priorités, les contraintes, les énoncés de tolérance au risque et d’appétit et les hypothèses de l’organisation sont établis, communiqués et utilisés pour soutenir les décisions en matière de risque opérationnel. | D4: GV. RM-03 : Les activités et les résultats de la gestion des risques liés à la cybersécurité sont inclus dans les processus de gestion des risques organisationnels. | E4: GV. RM-03.1 : Dans le cadre de la stratégie de gestion des risques à l’échelle de l’organisation, une stratégie globale de gestion des risques liés à l’information et à la cybersécurité doit être élaborée et mise à jour lorsque des changements se produisent. | F4: 1 | G4: 1 | H4: =AVERAGE(F4) -> 1 | I4: =AVERAGE(G4) -> 1 | J4: =H4 -> 1 | K4: =I4 -> 1
A5: Rôles, responsabilités et pouvoirs (GV. RR) : Les rôles, les responsabilités et les pouvoirs en matière de cybersécurité visant à favoriser la responsabilisation, l’évaluation du rendement et l’amélioration continue sont établis et communiqués. | D5: GV. RR-04 : La cybersécurité fait partie des pratiques en matière de ressources humaines. | E5: GV. RR-04.1 : Le personnel ayant accès à l’information ou à la technologie la plus critique de l’organisation doit être authentifié | F5: 1 | G5: 1 | H5: =AVERAGE(F5) -> 1 | I5: =AVERAGE(G5) -> 1 | J5: =H5 -> 1 | K5: =I5 -> 1
A6: Politique (GV. PO) : La politique de cybersécurité de l’organisation est établie, communiquée et appliquée. | D6: GV. OP-01 : La politique de gestion des risques de cybersécurité est établie en fonction du contexte organisationnel, de la stratégie de cybersécurité et des priorités, et est communiquée et appliquée. | E6: GV. OP-01.1 : Des politiques et des procédures de gestion de l’information et de cybersécurité doivent être établies, documentées, examinées, approuvées, mises à jour lorsque des changements se produisent, communiquées et appliquées. | F6: 1 | G6: 1 | H6: =AVERAGE(F6) -> 1 | I6: =AVERAGE(G6) -> 1 | J6: =H6 -> 1 | K6: =I6 -> 1

Sheet IDENTIFY
A1: TLP: AMBER CyberFundamentals Tool version: | C1: =Introduction!Q4 -> 45931 | D1: Self-Assessment Completion Date: | E1: =Introduction!T27 -> 45931 | F1: BASIC
A2: Categorie | B2: Mesure de gouvernance | C2: Mesure clé | D2: Sous categorie | E2: Exigence | F2: Documentation Score | G2: Score de mise en œuvre | H2: Sous-catégorie Documentation Score de maturité | I2: Sous-catégorie Score de maturité de la mise en œuvre | J2: Catégorie Documentation Maturité Score | K2: Catégorie : Score de maturité de mise en œuvre | L2: Commentaires et/ou informations complémentaires | M2: Commentaires de l’évaluateur
A3: Gestion des actifs (ID.AM) : Les actifs (par exemple, les données, le matériel, les logiciels, les systèmes, les installations, les services, les personnes) qui permettent à l’organisation d’atteindre ses objectifs commerciaux sont identifiés et gérés en fonction de leur importance relative par rapport aux objectifs organisationnels et à la stratégie de risque de l’organisation. | D3: ID.AM-01 : Les inventaires du matériel géré par l’organisation sont tenus. | E3: ID.AM-01.1 : Un inventaire des actifs d’infrastructure physique et virtuelle, tels que le matériel, les périphériques réseau et les environnements hébergés dans le cloud, qui prennent en charge le traitement de l’information doit être documenté, examiné et mis à jour au fur et à mesure que des changements se produisent. | F3: 1 | G3: 1 | H3: =AVERAGE(F3) -> 1 | I3: =AVERAGE(G3) -> 1 | J3: =AVERAGE(H3:H7) -> 1 | K3: =AVERAGE(I3:I7) -> 1
D4: ID.AM-02 : Des inventaires des logiciels, des services et des systèmes gérés par l’organisation sont tenus. | E4: ID.AM-02.1 : Un inventaire des logiciels, des services numériques et des systèmes d’entreprise utilisés au sein de l’organisation doit être documenté, examiné et mis à jour au fur et à mesure que des changements se produisent. | F4: 1 | G4: 1 | H4: =AVERAGE(F4) -> 1 | I4: =AVERAGE(G4) -> 1
D5: ID.AM-5 : Les ressources sont classées par ordre de priorité en fonction de la classification, de la criticité, des ressources et de l’impact sur la mission. | E5: ID.AM-5.1 : Les actifs de l’organisation doivent être classés par ordre de priorité en fonction de la classification, de la criticité et de la valeur commerciale. | F5: 1 | G5: 1 | H5: =AVERAGE(F5) -> 1 | I5: =AVERAGE(G5) -> 1
D6: ID.AM-07 : Des inventaires de données et les métadonnées correspondantes pour les types de données désignés sont tenus. | E6: ID.AM-07.1 : Les données que l’organisation stocke et utilise doivent être identifiées. | F6: 1 | G6: 1 | H6: =AVERAGE(F6) -> 1 | I6: =AVERAGE(G6) -> 1
C7: Mesure clé | D7: ID.AM-08 : Les systèmes, le matériel, les logiciels, les services et les données sont gérés tout au long de leur cycle de vie. | E7: ID.AM-08.2 : Des correctifs et des mises à jour de sécurité pour les systèmes d’exploitation et les composants critiques du système doivent être installés. | F7: 1 | G7: 1 | H7: =AVERAGE(F7) -> 1 | I7: =AVERAGE(G7) -> 1
A8: Évaluation des risques (ID.RA) : Le risque de cybersécurité pour l’organisation, les actifs et les individus est compris par l’organisation. | D8: ID.RA-01 : Les vulnérabilités des actifs sont identifiées, validées et enregistrées. | E8: ID.RA-01.1 : Les menaces et les vulnérabilités doivent être identifiées dans tous les biens pertinents, y compris les logiciels, les architectures de réseau et de système, et les installations qui hébergent des biens informatiques critiques. | F8: 1 | G8: 1 | H8: =AVERAGE(F8) -> 1 | I8: =AVERAGE(G8) -> 1 | J8: =AVERAGE(H8:H9) -> 1 | K8: =AVERAGE(I8:I9) -> 1
D9: ID.RA-05 : Les menaces, les vulnérabilités, les probabilités et les impacts sont utilisés pour comprendre le risque inhérent et éclairer la hiérarchisation de la réponse aux risques. | E9: ID.RA-05.1 : L’organisation doit effectuer des évaluations des risques dans lesquelles le risque est déterminé par les menaces, les vulnérabilités et l’impact sur les processus et les actifs de l’entreprise. | F9: 1 | G9: 1 | H9: =AVERAGE(F9) -> 1 | I9: =AVERAGE(G9) -> 1
A10: Amélioration (ID.IM) : Les améliorations apportées aux processus, procédures et activités de gestion des risques de cybersécurité organisationnels sont identifiées dans toutes les fonctions de CyFun©. | D10: ID.IM-03 : Des améliorations sont identifiées à partir de l’exécution des processus, procédures et activités opérationnels. | E10: ID.IM-03.1 : L’organisation doit effectuer des évaluations post-incident afin d’analyser les leçons tirées de la réponse et de la récupération en cas d’incident, et par conséquent d’améliorer les processus, les procédures et les technologies afin de renforcer sa cyber-résilience. | F10: 1 | G10: 1 | H10: =AVERAGE(F10) -> 1 | I10: =AVERAGE(G10) -> 1 | J10: =H10 -> 1 | K10: =I10 -> 1

Sheet PROTECT
A1: TLP: AMBER CyberFundamentals Tool version: | C1: =Introduction!Q4 -> 45931 | D1: Self-Assessment Completion Date: | E1: =Introduction!T27 -> 45931 | F1: BASIC
A2: Categorie | B2: Mesure de gouvernance | C2: Mesure clé | D2: Sous-catégorie | E2: Exigence | F2: Documentation Score | G2: Score de mise en œuvre | H2: Sous-catégorie Documentation Score de maturité | I2: Sous-catégorie Score de maturité de la mise en œuvre | J2: Catégorie Documentation Maturité Score | K2: Catégorie : Score de maturité de mise en œuvre | L2: Commentaires et/ou informations complémentaires | M2: Commentaires de l’évaluateur
A3: La gestion des identités, l’authentification et le contrôle d’accès (PR. AA) : L’accès aux actifs physiques et logiques est limité aux utilisateurs, aux services et au matériel autorisés et géré en fonction du risque évalué d’accès non autorisé. | C3: Mesure clé | D3: PR. AA-01 : Les identités et les informations d’identification des utilisateurs autorisés, des services et du matériel sont gérées par l’organisation. | E3: PR. AA-01.1 : Les identités et les identifiants des utilisateurs, des services et du matériel autorisés doivent être gérés. | F3: 1 | G3: 1 | H3: =AVERAGE(F3) -> 1 | I3: =AVERAGE(G3) -> 1 | J3: =AVERAGE(H3:H10) -> 1 | K3: =AVERAGE(I3:I10) -> 1
D4: PR. AA-03 : Les utilisateurs, les services et le matériel sont authentifiés. | E4: PR. AA-03.1 : Tous les points d’accès sans fil utilisés par l’organisation, y compris ceux qui fournissent un accès invité, doivent être configurés, gérés et surveillés en toute sécurité afin d’empêcher tout accès non autorisé et d’assurer l’intégrité du réseau. | F4: 1 | G4: 1 | H4: =AVERAGE(F4:F5) -> 1 | I4: =AVERAGE(G4:G5) -> 1
C5: Mesure clé | E5: PR. AA-03.2 : L’authentification multifactorielle (MFA) doit être requise pour accéder aux réseaux de l’organisation à distance. | F5: 1 | G5: 1
C6: Mesure clé | D6: PR. AA-05 : Les autorisations, les droits et les autorisations d’accès sont définis dans une politique, gérés, appliqués et révisés, et intègrent les principes du moindre privilège et de la séparation des tâches. | E6: PR. AA-05.1 : Les permissions, droits et autorisations d’accès doivent être définis, gérés, appliqués et révisés. | F6: 1 | G6: 1 | H6: =AVERAGE(F6:F9) -> 1 | I6: =AVERAGE(G6:G9) -> 1
C7: Mesure clé | E7: PR. AA-05.2 : Il faut déterminer qui a besoin d’accéder à l’information et à la technologie essentielles à l’entreprise de l’organisation et les moyens d’y accéder. | F7: 1 | G7: 1
C8: Mesure clé | E8: PR. AA-05.3 : Les droits d’accès, privilèges et autorisations doivent être limités aux systèmes et aux informations spécifiques nécessaires à l’exécution des tâches (principe du moindre privilège). | F8: 1 | G8: 1
C9: Mesure clé | E9: PR. AA-05.4 : Nul ne doit avoir de privilèges administratifs pour les tâches courantes de la vie quotidienne. | F9: 1 | G9: 1
D10: PR. AA-06 : L’accès physique aux actifs est géré, surveillé et appliqué en fonction du risque | E10: PR. AA-06.1 : L’accès physique à tous les biens de l’organisation, y compris les zones critiques, doit être géré, surveillé et appliqué en fonction du risque. | F10: 1 | G10: 1 | H10: =AVERAGE(F10) -> 1 | I10: =AVERAGE(G10) -> 1
A11: Sensibilisation et formation (PR. AT) : Le personnel de l’organisation reçoit une sensibilisation et une formation en cybersécurité afin qu’il puisse effectuer ses tâches liées à la cybersécurité | D11: PR. AT-01 : Le personnel reçoit une formation et une sensibilisation afin qu’il possède les connaissances et les compétences nécessaires pour effectuer des tâches générales en tenant compte des risques de cybersécurité. | E11: PR. AT-01.1 : L’organisation doit établir et tenir à jour un programme de sensibilisation et de formation en cybersécurité pour s’assurer que tout le personnel comprend comment effectuer ses tâches de manière sûre et responsable. | F11: 1 | G11: 1 | H11: =AVERAGE(F11) -> 1 | I11: =AVERAGE(G11) -> 1 | J11: =AVERAGE(H11) -> 1 | K11: =AVERAGE(I11) -> 1
A12: Sécurité des données (PR.DS) : Les données sont gérées conformément à la stratégie de risque de l’organisation afin de protéger la confidentialité, l’intégrité et la disponibilité des informations. | D12: PR. DS-01 : La confidentialité, l’intégrité et la disponibilité des données au repos sont protégées. | E12: PR. DS-01.9 : Les actifs de l’entreprise doivent être aliénés en toute sécurité. | F12: 1 | G12: 1 | H12: =AVERAGE(F12) -> 1 | I12: =AVERAGE(G12) -> 1 | J12: =AVERAGE(H12:H13) -> 1 | K12: =AVERAGE(I12:I13) -> 1
C13: Mesure clé | D13: PR. DS-11 : Les sauvegardes des données sont créées, protégées, maintenues et testées. | E13: PR. DS-11.1 : Les sauvegardes des données critiques de l’entreprise de l’organisation doivent être effectuées et stockées sur un système différent de l’appareil sur lequel résident les données d’origine. | F13: 1 | G13: 1 | H13: =AVERAGE(F13) -> 1 | I13: =AVERAGE(G13) -> 1
A14: Sécurité des plateformes (PR.PS) : Le matériel, les logiciels (par exemple, les micrologiciels, les systèmes d’exploitation, les applications) et les services des plateformes physiques et virtuelles sont gérés conformément à la stratégie de risque de l’organisation, afin de protéger leur confidentialité, leur intégrité et leur disponibilité | B14: Governance Measure | C14: Mesure clé | D14: PR. PS-04 : Les enregistrements de journal sont générés et mis à disposition pour une surveillance continue. | E14: PR. PS-04.1 : Les registres doivent être tenus, documentés et surveillés. | F14: 1 | G14: 1 | H14: =AVERAGE(F14) -> 1 | I14: =AVERAGE(G14) -> 1 | J14: =AVERAGE(H14:H15) -> 1 | K14: =AVERAGE(I14:I15) -> 1
D15: PR. PS-05 : L’installation et l’exécution de logiciels non autorisés sont empêchées. | E15: PR. PS-05.1 : Des filtres Web et de courrier électronique doivent être installés et utilisés. | F15: 1 | G15: 1 | H15: =AVERAGE(F15) -> 1 | I15: =AVERAGE(G15) -> 1
A16: Résilience de l’infrastructure technologique (PR.IR) : Les architectures de sécurité sont gérées avec la stratégie de risque de l’organisation, afin de protéger la confidentialité, l’intégrité et la disponibilité des actifs, ainsi que la résilience organisationnelle. | C16: Mesure clé | D16: PR. IR-01 : Les réseaux et les environnements sont protégés contre l’accès logique et l’utilisation non autorisés. | E16: PR. IR-01.1 : Des pare-feu doivent être installés, configurés et entretenus activement sur tous les réseaux utilisés par l’organisation pour se protéger contre les accès non autorisés et les cybermenaces. | F16: 1 | G16: 1 | H16: =AVERAGE(F16:F17) -> 1 | I16: =AVERAGE(G16:G17) -> 1 | J16: =AVERAGE(H16:H17) -> 1 | K16: =AVERAGE(I16:I17) -> 1
C17: Mesure clé | E17: PR. IR-01.2 : Pour protéger les systèmes critiques, les organisations doivent mettre en œuvre une segmentation et une ségrégation du réseau alignées sur les limites de confiance et la criticité des actifs, limitant ainsi la propagation des menaces et appliquant un contrôle d’accès strict. | F17: 1 | G17: 1

Sheet DETECT
A1: TLP: AMBER CyberFundamentals Tool version: | C1: =Introduction!Q4 -> 45931 | D1: Self-Assessment Completion Date: | E1: =Introduction!T27 -> 45931 | F1: BASIC
A2: Catégorie | B2: Mesure de gouvernance | C2: Mesure clé | D2: Sous-catégorie | E2: Exigence | F2: Documentation Score | G2: Score de mise en œuvre | H2: Sous-catégorie Documentation Score de maturité | I2: Sous-catégorie Score de maturité de la mise en œuvre | J2: Catégorie Documentation Maturité Score | K2: Catégorie : Score de maturité de mise en œuvre | L2: Commentaires et/ou informations complémentaires | M2: Commentaires de l’évaluateur
A3: Surveillance continue (DE. CM) : Les actifs sont surveillés pour détecter les anomalies, les indicateurs de compromission et d’autres événements potentiellement indésirables. | D3: DE. CM-01 : Les réseaux et les services de réseau sont surveillés afin de détecter les événements potentiellement indésirables. | E3: DE. CM-01.1 : Les pare-feu doivent être installés et exploités aux limites du réseau, y compris les pare-feu des points d’extrémité. | F3: 1 | G3: 1 | H3: =AVERAGE(F3:F4) -> 1 | I3: =AVERAGE(G3:G4) -> 1 | J3: =AVERAGE(H3:H5) -> 1 | K3: =AVERAGE(I3:I5) -> 1
C4: Mesure clé | E4: DE. CM-01.2 : Des antivirus, des logiciels espions et d’autres programmes malveillants doivent être installés et mis à jour. | F4: 1 | G4: 1
D5: DE. CM-03 : L’activité du personnel et l’utilisation de la technologie sont surveillées afin de détecter les événements potentiellement indésirables. | E5: DE. CM-03-1 : Des outils de protection des points d’extrémité et du réseau doivent être mis en œuvre pour surveiller le comportement de l’utilisateur final en cas d’activité dangereuse. | F5: 1 | G5: 1 | H5: =AVERAGE(F5) -> 1 | I5: =AVERAGE(G5) -> 1
A6: Analyse des événements indésirables (DE. AE) : Les anomalies, les indicateurs de compromission et d’autres événements potentiellement indésirables sont analysés pour caractériser les événements et détecter les incidents de cybersécurité. | C6: Mesure clé | D6: DE. AE-03 : L’information provient de sources multiples. | E6: DE. AE-03.1 : La fonctionnalité de journalisation des outils de protection et de détection doit être activée. Les registres doivent être sauvegardés pendant une période prédéfinie, puis régulièrement révisés afin de déceler les activités inhabituelles ou potentiellement nuisibles. | F6: 1 | G6: 1 | H6: =AVERAGE(F6) -> 1 | I6: =AVERAGE(G6) -> 1 | J6: =H6 -> 1 | K6: =I6 -> 1

Sheet RESPOND
A1: TLP: AMBER CyberFundamentals Tool version: | C1: =Introduction!Q4 -> 45931 | D1: Self-Assessment Completion Date: | E1: =Introduction!T27 -> 45931 | F1: BASIC
A2: Catégorie | B2: Mesure de gouvernance | C2: Mesure clé | D2: Sous-catégorie | E2: Exigence | F2: Documentation Score | G2: Score de mise en œuvre | H2: Sous-catégorie Documentation Score de maturité | I2: Sous-catégorie Score de maturité de la mise en œuvre | J2: Catégorie Documentation Maturité Score | K2: Catégorie : Score de maturité de mise en œuvre | L2: Commentaires et/ou informations complémentaires | M2: Commentaires de l’évaluateur
A3: Gestion des incidents (RS. MA) : Les réponses aux incidents de cybersécurité détectés sont gérées. | D3: RS. MA-01 : Le plan d’intervention en cas d’incident est exécuté en coordination avec les tiers concernés une fois qu’un incident est déclaré. | E3: RS. MA-01.1 : Un plan d’intervention en cas d’incident, y compris les rôles, les responsabilités et les pouvoirs définis, doit être exécuté pendant ou après un événement de cybersécurité touchant les systèmes critiques de l’organisation. | F3: 1 | G3: 1 | H3: =AVERAGE(F3) -> 1 | I3: =AVERAGE(G3) -> 1 | J3: =AVERAGE(H3) -> 1 | K3: =AVERAGE(I3) -> 1
A4: Rapports et communication (RS.CO) : Les activités d’intervention sont coordonnées avec les parties prenantes internes et externes, comme l’exigent les lois, les règlements ou les politiques. | D4: RS. CO-02 : Les intervenants internes et externes sont avisés des incidents. | E4: RS. CO-02.1 : L’information sur les incidents de cybersécurité doit être communiquée aux employés d’une manière claire et facile à comprendre. | F4: 1 | G4: 1 | H4: =AVERAGE(F4) -> 1 | I4: =AVERAGE(G4) -> 1 | J4: =AVERAGE(H4) -> 1 | K4: =AVERAGE(I4) -> 1

Sheet RECOVER
A1: TLP: AMBER CyberFundamentals Tool version: | C1: =Introduction!Q4 -> 45931 | D1: Self-Assessment Completion Date: | E1: =Introduction!T27 -> 45931 | F1: BASIC
A2: Catégorie | B2: Mesure de gouvernance | C2: Mesure clé | D2: Sous-catégorie | E2: Exigence | F2: Documentation Score | G2: Score de mise en œuvre | H2: Sous-catégorie Documentation Score de maturité | I2: Sous-catégorie Score de maturité de la mise en œuvre | J2: Catégorie Documentation Maturité Score | K2: Catégorie : Score de maturité de mise en œuvre | L2: Commentaires et/ou informations complémentaires | M2: Commentaires de l’évaluateur
A3: Exécution du plan de récupération d’incident (RC. RP) : Des activités de restauration sont réalisées pour assurer la disponibilité opérationnelle des systèmes et services affectés par des incidents de cybersécurité. | D3: RC. PR-01 : La partie rétablissement du plan d’intervention en cas d’incident est exécutée une fois qu’elle a été amorcée à partir du processus d’intervention en cas d’incident. | E3: RC. PR-01.1 : Un processus de rétablissement en cas de catastrophe et d’incident lié à l’information ou à la cybersécurité doit être élaboré et mis en œuvre. | F3: 1 | G3: 1 | H3: =F3 -> 1 | I3: =G3 -> 1 | J3: =AVERAGE(H3) -> 1 | K3: =AVERAGE(I3) -> 1

Sheet BASIC Summary
B2: CyberFundamentals Categories | C2: Target Maturity Score | D2: Maturity Score | E2: Documentation Maturity Score | F2: Implementation Maturity Score | M2: Total Maturity level
B4: Overall | C4: 2.5 | E4: =AVERAGE(E5:E21) -> 1 | F4: =AVERAGE(F5:F21) -> 1 | M4: =SUM(D5:D21)/COUNT(D5:D21) -> 1
A5: GOVEN | B5: Organisational Context (GV.OC) | D5: =AVERAGE(E5:F5) -> 1 | E5: =GOVERN!J3 -> 1 | F5: =GOVERN!K3 -> 1
B6: Risk Management Strategy (GV.RM) | D6: =AVERAGE(E6:F6) -> 1 | E6: =GOVERN!J4 -> 1 | F6: =GOVERN!K4 -> 1 | M6: TLP: AMBER
B7: Roles, Responsibilities, and Authorities (GV.RR) | D7: =AVERAGE(E7:F7) -> 1 | E7: =GOVERN!J5 -> 1 | F7: =GOVERN!K5 -> 1
B8: Policy (GV.PO) | D8: =AVERAGE(E8:F8) -> 1 | E8: =GOVERN!J6 -> 1 | F8: =GOVERN!K6 -> 1
A9: IDENTIFY | B9: Asset Management (ID.AM) | D9: =AVERAGE(E9:F9) -> 1 | E9: =IDENTIFY!J3 -> 1 | F9: =IDENTIFY!K3 -> 1 | M9: CyberFundamentals Self-Assesment | N9: Tool Version | O9: =Introduction!Q4 -> 45931
B10: Risk Assessment (ID.RA) | D10: =AVERAGE(E10:F10) -> 1 | E10: =IDENTIFY!J8 -> 1 | F10: =IDENTIFY!K8 -> 1
B11: Improvement (ID.IM) | D11: =AVERAGE(E11:F11) -> 1 | E11: =IDENTIFY!J10 -> 1 | F11: =IDENTIFY!K10 -> 1 | M11: Self-Assessment Completion date | N11: =Introduction!T27 -> 45931
A12: PROTECT | B12: Identity Management, Authentication, and Access Control (PR.AA) | D12: =AVERAGE(E12:F12) -> 1 | E12: =PROTECT!J3 -> 1 | F12: =PROTECT!K3 -> 1
B13: Awareness and Training (PR.AT) | D13: =AVERAGE(E13:F13) -> 1 | E13: =PROTECT!J11 -> 1 | F13: =PROTECT!K11 -> 1
B14: Data Security (PR.DS) | D14: =AVERAGE(E14:F14) -> 1 | E14: =PROTECT!J12 -> 1 | F14: =PROTECT!K12 -> 1
B15: Platform Security (PR.PS) | D15: =AVERAGE(E15:F15) -> 1 | E15: =PROTECT!J14 -> 1 | F15: =PROTECT!K14 -> 1
B16: Technology Infrastructure Resilience (PR.IR) | D16: =AVERAGE(E16:F16) -> 1 | E16: =PROTECT!J16 -> 1 | F16: =PROTECT!K16 -> 1
A17: DETECT | B17: Continuous Monitoring (DE.CM) | D17: =AVERAGE(E17:F17) -> 1 | E17: =DETECT!J3 -> 1 | F17: =DETECT!K3 -> 1
B18: Adverse Event Analysis (DE.AE) | D18: =AVERAGE(E18:F18) -> 1 | E18: =DETECT!J6 -> 1 | F18: =DETECT!K6 -> 1
A19: RESPOND | B19: Incident Management (RS.MA) | D19: =AVERAGE(E19:F19) -> 1 | E19: =RESPOND!J3 -> 1 | F19: =RESPOND!K3 -> 1
B20: Incident Response Reporting and Communication (RS.CO) | D20: =AVERAGE(E20:F20) -> 1 | E20: =RESPOND!J4 -> 1 | F20: =RESPOND!K4 -> 1
A21: RECOVER | B21: Incident Recovery Plan Execution (RC.RP) | D21: =AVERAGE(E21:F21) -> 1 | E21: =RECOVER!J3 -> 1 | F21: =RECOVER!K3 -> 1
L23: MESURES CLÉS (KM)
L24: Exigence | N24: Score de maturité cible | O24: Score de maturité KM | P24: Score de maturité de la documentation | Q24: Score de maturité de la mise en œuvre
L25: ID.AM-08.2 | M25: Des correctifs et des mises à jour de sécurité pour les systèmes d’exploitation et les composants critiques du système doivent être installés. | N25: 2.5 | O25: =AVERAGE(P25,Q25) -> 1 | P25: =IDENTIFY!F7 -> 1 | Q25: =IDENTIFY!G7 -> 1
L26: PR.AA-01.1 | M26: Les identités et les informations d’identification des utilisateurs autorisés, des services et du matériel doivent être gérées. | N26: 2.5 | O26: =AVERAGE(P26,Q26) -> 1 | P26: =PROTECT!F3 -> 1 | Q26: =PROTECT!G3 -> 1
L27: PR.AA-03.2 | M27: L’authentification multifacteur (MFA) est requise pour accéder à distance aux réseaux de l’organisation. | N27: 2.5 | O27: =AVERAGE(P27,Q27) -> 1 | P27: =PROTECT!F5 -> 1 | Q27: =PROTECT!G5 -> 1
L28: PR.AA-05.1 | M28: Les autorisations, droits et autorisations d’accès doivent être définis, gérés, appliqués et révisés. | N28: 2.5 | O28: =AVERAGE(P28,Q28) -> 1 | P28: =PROTECT!F6 -> 1 | Q28: =PROTECT!G6 -> 1
L29: PR.AA-05.2 | M29: Il s’agit de déterminer qui a besoin d’accéder aux informations et aux technologies critiques de l’organisation et les moyens d’y accéder. | N29: 2.5 | O29: =AVERAGE(P29,Q29) -> 1 | P29: =PROTECT!F7 -> 1 | Q29: =PROTECT!G7 -> 1
L30: PR.AA-05.3 | M30: Les droits d’accès, les privilèges et les autorisations sont limités aux systèmes et aux informations spécifiques nécessaires à l’exécution des tâches (principe du moindre privilège). | N30: 2.5 | O30: =AVERAGE(P30,Q30) -> 1 | P30: =PROTECT!F8 -> 1 | Q30: =PROTECT!G8 -> 1
L31: PR.AA-05.4 | M31: Nul ne peut jouir de privilèges administratifs pour les tâches courantes de la vie courante. | N31: 2.5 | O31: =AVERAGE(P31,Q31) -> 1 | P31: =PROTECT!F9 -> 1 | Q31: =PROTECT!G9 -> 1
L32: PR.DS-11.1 | M32: Les sauvegardes des données critiques de l’entreprise doivent être effectuées et stockées sur un système différent de l’appareil sur lequel résident les données d’origine. | N32: 2.5 | O32: =AVERAGE(P32:Q32) -> 1 | P32: =PROTECT!H13 -> 1 | Q32: =PROTECT!I13 -> 1
L33: PR.PS-04.1 | M33: Les registres doivent être tenus, documentés et surveillés. | N33: 2.5 | O33: =AVERAGE(P33:Q33) -> 1 | P33: =PROTECT!H14 -> 1 | Q33: =PROTECT!I14 -> 1
L34: PR.IR-01.1 | M34: Des pare-feu doivent être installés, configurés et activement entretenus sur tous les réseaux utilisés par l’organisation pour se protéger contre les accès non autorisés et les cybermenaces. | N34: 2.5 | O34: =AVERAGE(P34:Q34) -> 1 | P34: =PROTECT!F16 -> 1 | Q34: =PROTECT!G16 -> 1
L35: PR.IR-01.2 | M35: Pour protéger les systèmes critiques, les organisations doivent mettre en œuvre une segmentation et une ségrégation du réseau alignées sur les limites de confiance et la criticité des actifs, limitant ainsi la propagation des menaces et appliquant un contrôle d’accès strict. | N35: 2.5 | O35: =AVERAGE(P35,Q35) -> 1 | P35: =PROTECT!F17 -> 1 | Q35: =PROTECT!G17 -> 1
L36: DE.CM-01.2 | M36: Des antivirus, des logiciels espions et d’autres programmes malveillants doivent être installés et mis à jour. | N36: 2.5 | O36: =AVERAGE(P36,Q36) -> 1 | P36: =DETECT!F4 -> 1 | Q36: =DETECT!G4 -> 1
L37: DE.AE-03.1 | M37: La fonctionnalité d’enregistrement des outils de protection et de détection doit être activée. Les registres doivent être sauvegardés et conservés pendant une période prédéfinie, et régulièrement révisés afin de déceler les activités inhabituelles ou potentiellement nuisibles. | N37: 2.5 | O37: =AVERAGE(P37,Q37) -> 1 | P37: =DETECT!F6 -> 1 | Q37: =DETECT!G6 -> 1

Sheet Sheet1
B2: 1
B3: 2
B4: 3
B5: 4
B6: 5

Sheet References
A1: Document | B1: Link
A2: CIS Critical Security Control | B2: https://www.cisecurity.org/controls/
A3: ISA 62443 (All) | B3: https://www.isa.org/standards-and-publications/isa-standards/find-isa-standards-in-numerical-order/
A4: ISO/IEC 27001 | B4: https://www.iso.org/standard/27001
A5: ISO/IEC 27002 | B5: https://www.iso.org/standard/75652.html
A6: NIST CSF | B6: https://www.nist.gov/cyberframework
